app/__init__.py
app/__main__.py
app/version.py
app/data/__init__.py
app/data/config/__init__.py
app/data/config/db_base.py
app/data/config/db_config.py
app/data/repositories/__init__.py
app/data/repositories/user_respository.py
app/domain/__init__.py
app/domain/dtos/__init__.py
app/domain/dtos/user.py
app/domain/entities/__init__.py
app/domain/entities/base.py
app/domain/entities/user.py
app/domain/use_cases/__init__.py
app/domain/use_cases/user_use_case.py
app/modules/__init__.py
app/modules/cli/__init__.py
app/modules/cli/user_cli.py
app/modules/console/__init__.py
app/modules/console/badvpn_console.py
app/modules/console/openvpn_console.py
app/modules/console/socks_console.py
app/modules/console/tools_console.py
app/modules/console/user_console.py
app/modules/console/utils.py
app/modules/console/v2ray_console.py
app/modules/console/ovpn_utils/__init__.py
app/modules/console/ovpn_utils/install.py
app/modules/console/ovpn_utils/manager.py
app/modules/console/ovpn_utils/utils.py
app/modules/console/v2ray_utils/__init__.py
app/modules/console/v2ray_utils/config.py
app/modules/console/v2ray_utils/manager.py
app/modules/console/v2ray_utils/utils.py
app/serializers/__init__.py
app/serializers/serializer.py
app/utilities/__init__.py
app/utilities/logger.py
app/utilities/shellscript.py
app/utilities/utils.py
app/utilities/v2ray_config_template.py
app/utilities/validators.py
bot/__init__.py
bot/__main__.py
bot/commands/__init__.py
bot/commands/create_user.py
bot/commands/dealer.py
bot/commands/delete_user.py
bot/commands/details_user.py
bot/commands/helper.py
bot/commands/list_users.py
bot/commands/message_helper.py
bot/commands/monitor.py
bot/commands/helpers/__init__.py
bot/commands/helpers/dealer.py
bot/config/__init__.py
bot/config/bot_config.py
bot/config/config.py
bot/dealer/__init__.py
bot/dealer/respository.py
bot/dealer/use_case.py
bot/middleware/__init__.py
bot/middleware/permisson.py
bot/utilities/__init__.py
bot/utilities/utils.py
console/__init__.py
GLManager-1.1.6.dist-info/METADATA
GLManager-1.1.6.dist-info/WHEEL
GLManager-1.1.6.dist-info/entry_points.txt
GLManager-1.1.6.dist-info/top_level.txt
GLManager-1.1.6.dist-info/RECORD
