Metadata-Version: 2.1
Name: GLManager
Version: 1.1.6
Home-page: https://github.com/DuTra01/GLManager.git
Author: Glemison C. DuTra
Author-email: glemyson20@gmail.com
License: MIT
Platform: linux
Requires-Dist: sqlalchemy
Requires-Dist: pytest
Requires-Dist: distro
Requires-Dist: pytelegrambotapi (==4.6.0)
Requires-Dist: python-daemon
